python_project_RD/__init__.py
python_project_RD/CHANGELOG.md
python_project_RD/extra_broker.py
python_project_RD/extra_modules.py
python_project_RD/python_project.py
python_project_RD/user_function.py
python_project_rd-0.5.0.dist-info/LICENSE
python_project_rd-0.5.0.dist-info/METADATA
python_project_rd-0.5.0.dist-info/WHEEL
python_project_rd-0.5.0.dist-info/RECORD
